databricks_converter/__init__.py
databricks_converter/__main__.py
databricks_converter/__version__.py
databricks_converter/constants.py
databricks_converter/converter/__init__.py
databricks_converter/converter/converter.py
databricks_converter/databricks2py/__init__.py
databricks_converter/databricks2py/converter.py
databricks_converter/databricks2py/utils.py
databricks_converter/py2Databricks/__init__.py
databricks_converter/py2Databricks/converter.py
databricks_converter/py2Databricks/utils.py
databricks_converter-0.0.9.dist-info/LICENSE
databricks_converter-0.0.9.dist-info/METADATA
databricks_converter-0.0.9.dist-info/WHEEL
databricks_converter-0.0.9.dist-info/entry_points.txt
databricks_converter-0.0.9.dist-info/top_level.txt
databricks_converter-0.0.9.dist-info/RECORD
