Metadata-Version: 2.1
Name: databricks-converter
Version: 0.0.9
Summary: It should convert a python module to databricks and viceversa.
Home-page: https://github.com/aless10/convert-py-2-databricks
Author: aless10
License: LICENSE
Project-URL: Bug Tracker, https://github.com/aless10/convert-py-2-databricks/issues
Platform: UNKNOWN
Classifier: Development Status :: 4 - Beta
Classifier: Intended Audience :: Developers
Classifier: License :: OSI Approved :: MIT License
Classifier: Programming Language :: Python
Classifier: Programming Language :: Python :: 3
Classifier: Programming Language :: Python :: 3.6
Classifier: Programming Language :: Python :: 3.7
Classifier: Programming Language :: Python :: 3.8
Classifier: Programming Language :: Python :: 3.9
Classifier: Programming Language :: Python :: Implementation :: PyPy
Classifier: Topic :: Software Development :: Libraries :: Python Modules
Requires-Dist: attrs (==21.2.0)
Requires-Dist: click (==8.0.1)
Requires-Dist: iniconfig (==1.1.1)
Requires-Dist: packaging (==20.9)
Requires-Dist: pluggy (==0.13.1)
Requires-Dist: py (==1.10.0)
Requires-Dist: pyparsing (==2.4.7)
Requires-Dist: pytest (==6.2.4)
Requires-Dist: toml (==0.10.2)
